Metadata-Version: 1.1
Name: get-key
Version: 1.60.0
Summary: Raw read single characters and key-strokes
Home-page: https://github.com/TheIceBergBot/getkey
Author: TheIceBergBot
Author-email: mydadisbrave4@gmail.com
License: MIT
Keywords: stdin,command line,keypress,getkey,get keypress
Platform: UNKNOWN
Classifier: Development Status :: 5 - Production/Stable
Classifier: Environment :: Console
Classifier: Intended Audience :: Developers
Classifier: License :: OSI Approved :: MIT License
Classifier: Operating System :: OS Independent
Classifier: Programming Language :: Python :: 2.7
Classifier: Programming Language :: Python :: 3.3
Classifier: Programming Language :: Python :: 3.4
Classifier: Programming Language :: Python :: 3.5
Classifier: Programming Language :: Python :: 3.6
Classifier: Programming Language :: Python :: 3.7
Classifier: Programming Language :: Python :: 3.8
Classifier: Programming Language :: Python :: 3.9
Classifier: Programming Language :: Python :: 3.10
Classifier: Topic :: Software Development
Classifier: Topic :: Software Development :: User Interfaces
